scrapkit/__init__.py
scrapkit/main.py
scrapkit-2.2.dist-info/METADATA
scrapkit-2.2.dist-info/WHEEL
scrapkit-2.2.dist-info/top_level.txt
scrapkit-2.2.dist-info/RECORD
