Metadata-Version: 2.1
Name: scrapkit
Version: 2.2
Summary: WebScrapping in 3 lines of code
Author: Ali Lodhi
Author-email: alilodhibusiness@gmail.com
Requires-Dist: requests ==2.31.0
Requires-Dist: bs4 ==0.0.2
Requires-Dist: sapit ==1.5
